[
	[
		{
			"morph_type": "complex",
			"list_index": 4,
			"indice": 59,
			"target": "jealousy",
			"preview": "gelosia ",
			"sentence": "They displayed a certain X over Audrey's sudden freedom.",
			"sentence_len": 63,
			"pre_target": "They displayed a certain ",
			"post_target": " over Audrey's sudden freedom.",
			"boundary_index": 24,
			"boundary_shift": -216
		},
		{
			"morph_type": "complex",
			"list_index": 1,
			"indice": 51,
			"target": "violence",
			"preview": "violence",
			"sentence": "If you promote X then it might be used on you too.",
			"sentence_len": 57,
			"pre_target": "If you promote ",
			"post_target": " then it might be used on you too.",
			"boundary_index": 14,
			"boundary_shift": -376
		},
		{
			"morph_type": "simple",
			"list_index": 4,
			"indice": 6,
			"target": "island",
			"preview": "isola ",
			"sentence": "The beauty of this\u00a0amazing X is one of my best memories.",
			"sentence_len": 61,
			"pre_target": "The beauty of this\u00a0amazing ",
			"post_target": " is one of my best memories.",
			"boundary_index": 26,
			"boundary_shift": -184
		},
		{
			"morph_type": "complex",
			"list_index": 3,
			"indice": 61,
			"target": "vastness",
			"preview": "vastit\u00e0 ",
			"sentence": "The snowy white X of the North Pole makes it difficult to survive.",
			"sentence_len": 73,
			"pre_target": "The snowy white ",
			"post_target": " of the North Pole makes it difficult to survive.",
			"boundary_index": 15,
			"boundary_shift": -360
		},
		{
			"morph_type": "simple",
			"list_index": 3,
			"indice": 9,
			"target": "molecule",
			"preview": "maledule",
			"sentence": "For the journey every\u00a0X will be reused in this sustainable spaceship.",
			"sentence_len": 76,
			"pre_target": "For the journey every\u00a0",
			"post_target": " will be reused in this sustainable spaceship.",
			"boundary_index": 21,
			"boundary_shift": -264
		},
		{
			"morph_type": "simple",
			"list_index": 3,
			"indice": 19,
			"target": "resource",
			"preview": "selorca ",
			"sentence": "The course introduces X management to combat global warning.",
			"sentence_len": 67,
			"pre_target": "The course introduces ",
			"post_target": " management to combat global warning.",
			"boundary_index": 21,
			"boundary_shift": -264
		},
		{
			"morph_type": "complex",
			"list_index": 2,
			"indice": 37,
			"target": "furious",
			"preview": "wlxdhty",
			"sentence": "I'm still increadibly X that I wasn't invited to the birthday party.",
			"sentence_len": 74,
			"pre_target": "I'm still increadibly ",
			"post_target": " that I wasn't invited to the birthday party.",
			"boundary_index": 21,
			"boundary_shift": -264
		},
		{
			"morph_type": "simple",
			"list_index": 1,
			"indice": 23,
			"target": "spinach",
			"preview": "slinaco",
			"sentence": "After a short wait seven X bowls were brought to the table.",
			"sentence_len": 65,
			"pre_target": "After a short wait seven ",
			"post_target": " bowls were brought to the table.",
			"boundary_index": 24,
			"boundary_shift": -216
		},
		{
			"morph_type": "complex",
			"list_index": 1,
			"indice": 58,
			"target": "humidity",
			"preview": "humidity",
			"sentence": "I think higher X feels worse than having higher temperatures.",
			"sentence_len": 68,
			"pre_target": "I think higher ",
			"post_target": " feels worse than having higher temperatures.",
			"boundary_index": 14,
			"boundary_shift": -376
		},
		{
			"morph_type": "complex",
			"list_index": 1,
			"indice": 46,
			"target": "genetics",
			"preview": "gedetici",
			"sentence": "That is not about X but rather about how you were raised.",
			"sentence_len": 64,
			"pre_target": "That is not about ",
			"post_target": " but rather about how you were raised.",
			"boundary_index": 17,
			"boundary_shift": -328
		},
		{
			"morph_type": "simple",
			"list_index": 4,
			"indice": 29,
			"target": "trumpet",
			"preview": "tromba ",
			"sentence": "A badly broken X lay in the middle of the deserted stage.",
			"sentence_len": 63,
			"pre_target": "A badly broken ",
			"post_target": " lay in the middle of the deserted stage.",
			"boundary_index": 14,
			"boundary_shift": -376
		},
		{
			"morph_type": "simple",
			"list_index": 4,
			"indice": 18,
			"target": "recruit",
			"preview": "recluta",
			"sentence": "His recent favourite X was a tall muscular boy named Peter.",
			"sentence_len": 65,
			"pre_target": "His recent favourite ",
			"post_target": " was a tall muscular boy named Peter.",
			"boundary_index": 20,
			"boundary_shift": -280
		},
		{
			"morph_type": "complex",
			"list_index": 4,
			"indice": 57,
			"target": "historic",
			"preview": "storico ",
			"sentence": "What an excitingly X setting for the last race of the season.",
			"sentence_len": 68,
			"pre_target": "What an excitingly ",
			"post_target": " setting for the last race of the season.",
			"boundary_index": 18,
			"boundary_shift": -312
		},
		{
			"morph_type": "complex",
			"list_index": 4,
			"indice": 39,
			"target": "signals",
			"preview": "mdhvcrk",
			"sentence": "Maybe some of those X aren't coming from outer space.",
			"sentence_len": 59,
			"pre_target": "Maybe some of those ",
			"post_target": " aren't coming from outer space.",
			"boundary_index": 19,
			"boundary_shift": -296
		},
		{
			"morph_type": "simple",
			"list_index": 4,
			"indice": 7,
			"target": "lettuce",
			"preview": "bvqsyzf",
			"sentence": "This will keep your X fresh and crunchy all week long.",
			"sentence_len": 60,
			"pre_target": "This will keep your ",
			"post_target": " fresh and crunchy all week long.",
			"boundary_index": 19,
			"boundary_shift": -296
		},
		{
			"morph_type": "simple",
			"list_index": 3,
			"indice": 17,
			"target": "prophet",
			"preview": "troglet",
			"sentence": "He found the young X at the back of the church.",
			"sentence_len": 53,
			"pre_target": "He found the young ",
			"post_target": " at the back of the church.",
			"boundary_index": 18,
			"boundary_shift": -312
		},
		{
			"morph_type": "complex",
			"list_index": 3,
			"indice": 62,
			"target": "asthmatic",
			"preview": "asmatico ",
			"sentence": "He quickly became X and had trouble breathing.",
			"sentence_len": 54,
			"pre_target": "He quickly became ",
			"post_target": " and had trouble breathing.",
			"boundary_index": 17,
			"boundary_shift": -328
		},
		{
			"morph_type": "simple",
			"list_index": 2,
			"indice": 8,
			"target": "marathon",
			"preview": "marathon",
			"sentence": "He missed the previous X and the one before that because of an injury.",
			"sentence_len": 77,
			"pre_target": "He missed the previous ",
			"post_target": " and the one before that because of an injury.",
			"boundary_index": 22,
			"boundary_shift": -248
		},
		{
			"morph_type": "complex",
			"list_index": 3,
			"indice": 38,
			"target": "nervous",
			"preview": "nervoso",
			"sentence": "With an increasingly X energy she ran faster and faster.",
			"sentence_len": 62,
			"pre_target": "With an increasingly ",
			"post_target": " energy she ran faster and faster.",
			"boundary_index": 20,
			"boundary_shift": -280
		},
		{
			"morph_type": "simple",
			"list_index": 4,
			"indice": 29,
			"target": "trumpet",
			"preview": "ljxwfdv",
			"sentence": "You shall be a fearless X of truth and a voice of godly influence.",
			"sentence_len": 72,
			"pre_target": "You shall be a fearless ",
			"post_target": " of truth and a voice of godly influence.",
			"boundary_index": 23,
			"boundary_shift": -232
		},
		{
			"morph_type": "simple",
			"list_index": 4,
			"indice": 2,
			"target": "genius",
			"preview": "tvkxmh",
			"sentence": "She is one of those X characters who don't work hard but succeed.",
			"sentence_len": 70,
			"pre_target": "She is one of those ",
			"post_target": " characters who don't work hard but succeed.",
			"boundary_index": 19,
			"boundary_shift": -296
		},
		{
			"morph_type": "complex",
			"list_index": 4,
			"indice": 63,
			"target": "luxurious",
			"preview": "lussuoso ",
			"sentence": "Sasha definitely had X tastes when it came to desserts.",
			"sentence_len": 63,
			"pre_target": "Sasha definitely had ",
			"post_target": " tastes when it came to desserts.",
			"boundary_index": 20,
			"boundary_shift": -280
		},
		{
			"morph_type": "simple",
			"list_index": 4,
			"indice": 22,
			"target": "sphere",
			"preview": "vgqmxl",
			"sentence": "Inside there was a light X resting on a pillow.",
			"sentence_len": 52,
			"pre_target": "Inside there was a light ",
			"post_target": " resting on a pillow.",
			"boundary_index": 24,
			"boundary_shift": -216
		},
		{
			"morph_type": "simple",
			"list_index": 2,
			"indice": 11,
			"target": "nephew",
			"preview": "nephew",
			"sentence": "This time his wonderful X was there for Ben during his breakdown.",
			"sentence_len": 70,
			"pre_target": "This time his wonderful ",
			"post_target": " was there for Ben during his breakdown.",
			"boundary_index": 23,
			"boundary_shift": -232
		},
		{
			"morph_type": "simple",
			"list_index": 2,
			"indice": 15,
			"target": "plaque",
			"preview": "brjtsd",
			"sentence": "The best way to eliminate X between your teeth is brushing them well.",
			"sentence_len": 74,
			"pre_target": "The best way to eliminate ",
			"post_target": " between your teeth is brushing them well.",
			"boundary_index": 25,
			"boundary_shift": -200
		},
		{
			"morph_type": "simple",
			"list_index": 4,
			"indice": 22,
			"target": "sphere",
			"preview": "sfera ",
			"sentence": "At home their X of influence drew them all in.",
			"sentence_len": 51,
			"pre_target": "At home their ",
			"post_target": " of influence drew them all in.",
			"boundary_index": 13,
			"boundary_shift": -392
		},
		{
			"morph_type": "complex",
			"list_index": 4,
			"indice": 63,
			"target": "luxurious",
			"preview": "tpchgfdjk",
			"sentence": "They were moved to relatively X quarters after they complained.",
			"sentence_len": 71,
			"pre_target": "They were moved to relatively ",
			"post_target": " quarters after they complained.",
			"boundary_index": 29,
			"boundary_shift": -136
		},
		{
			"morph_type": "simple",
			"list_index": 2,
			"indice": 27,
			"target": "theorem",
			"preview": "wnbpjdc",
			"sentence": "It is a solid X now despite the time it took to prove it.",
			"sentence_len": 63,
			"pre_target": "It is a solid ",
			"post_target": " now despite the time it took to prove it.",
			"boundary_index": 13,
			"boundary_shift": -392
		},
		{
			"morph_type": "complex",
			"list_index": 3,
			"indice": 61,
			"target": "vastness",
			"preview": "virteso ",
			"sentence": "She dreamt about green X filled with sweeping winds and fishing boats.",
			"sentence_len": 77,
			"pre_target": "She dreamt about green ",
			"post_target": " filled with sweeping winds and fishing boats.",
			"boundary_index": 22,
			"boundary_shift": -248
		},
		{
			"morph_type": "simple",
			"list_index": 1,
			"indice": 5,
			"target": "hygiene",
			"preview": "agiene ",
			"sentence": "You need good X if you're going to succeed at the interview.",
			"sentence_len": 66,
			"pre_target": "You need good ",
			"post_target": " if you're going to succeed at the interview.",
			"boundary_index": 13,
			"boundary_shift": -392
		},
		{
			"morph_type": "complex",
			"list_index": 2,
			"indice": 52,
			"target": "dignified",
			"preview": "lpxqhcvkm",
			"sentence": "He doesn't deserve a graceful X exit after what he's done.",
			"sentence_len": 66,
			"pre_target": "He doesn't deserve a graceful ",
			"post_target": " exit after what he's done.",
			"boundary_index": 29,
			"boundary_shift": -136
		},
		{
			"morph_type": "complex",
			"list_index": 3,
			"indice": 47,
			"target": "glorious",
			"preview": "groritus",
			"sentence": "He would have been truly X as a king in his prime.",
			"sentence_len": 57,
			"pre_target": "He would have been truly ",
			"post_target": " as a king in his prime.",
			"boundary_index": 24,
			"boundary_shift": -216
		},
		{
			"morph_type": "simple",
			"list_index": 4,
			"indice": 6,
			"target": "island",
			"preview": "yrbgqh",
			"sentence": "Our own little X of personal space is our table in the restaurant.",
			"sentence_len": 71,
			"pre_target": "Our own little ",
			"post_target": " of personal space is our table in the restaurant.",
			"boundary_index": 14,
			"boundary_shift": -376
		},
		{
			"morph_type": "complex",
			"list_index": 1,
			"indice": 34,
			"target": "acidity",
			"preview": "acidity",
			"sentence": "You can increase X by adding lemon juice to the mixture.",
			"sentence_len": 62,
			"pre_target": "You can increase ",
			"post_target": " by adding lemon juice to the mixture.",
			"boundary_index": 16,
			"boundary_shift": -344
		},
		{
			"morph_type": "simple",
			"list_index": 4,
			"indice": 24,
			"target": "sponge",
			"preview": "qmxhkc",
			"sentence": "This type of natural X is exactly what you need to clean your house.",
			"sentence_len": 73,
			"pre_target": "This type of natural ",
			"post_target": " is exactly what you need to clean your house.",
			"boundary_index": 20,
			"boundary_shift": -280
		},
		{
			"morph_type": "complex",
			"list_index": 3,
			"indice": 56,
			"target": "european",
			"preview": "europeo ",
			"sentence": "Half of the recent X car sales are reported to be electric cars.",
			"sentence_len": 71,
			"pre_target": "Half of the recent ",
			"post_target": " car sales are reported to be electric cars.",
			"boundary_index": 18,
			"boundary_shift": -312
		},
		{
			"morph_type": "complex",
			"list_index": 1,
			"indice": 34,
			"target": "acidity",
			"preview": "agidito",
			"sentence": "Some slight additional X can always improve the taste.",
			"sentence_len": 60,
			"pre_target": "Some slight additional ",
			"post_target": " can always improve the taste.",
			"boundary_index": 22,
			"boundary_shift": -248
		},
		{
			"morph_type": "simple",
			"list_index": 3,
			"indice": 28,
			"target": "throne",
			"preview": "trono ",
			"sentence": "The small wooden X for the prince sat at the head of the table.",
			"sentence_len": 68,
			"pre_target": "The small wooden ",
			"post_target": " for the prince sat at the head of the table.",
			"boundary_index": 16,
			"boundary_shift": -344
		},
		{
			"morph_type": "complex",
			"list_index": 2,
			"indice": 45,
			"target": "fortress",
			"preview": "fortress",
			"sentence": "She told us about the black X on a hill above all the land.",
			"sentence_len": 66,
			"pre_target": "She told us about the black ",
			"post_target": " on a hill above all the land.",
			"boundary_index": 27,
			"boundary_shift": -168
		},
		{
			"morph_type": "complex",
			"list_index": 1,
			"indice": 49,
			"target": "pianists",
			"preview": "peaniste",
			"sentence": "It's impressive how prettily X improvise when playing jazz.",
			"sentence_len": 66,
			"pre_target": "It's impressive how prettily ",
			"post_target": " improvise when playing jazz.",
			"boundary_index": 28,
			"boundary_shift": -152
		},
		{
			"morph_type": "simple",
			"list_index": 2,
			"indice": 8,
			"target": "marathon",
			"preview": "vfcgszwk",
			"sentence": "The important thing during X training is not to run too quickly.",
			"sentence_len": 71,
			"pre_target": "The important thing during ",
			"post_target": " training is not to run too quickly.",
			"boundary_index": 26,
			"boundary_shift": -184
		},
		{
			"morph_type": "simple",
			"list_index": 2,
			"indice": 14,
			"target": "parcel",
			"preview": "parcel",
			"sentence": "There was a large X on her doorstep when she got home.",
			"sentence_len": 59,
			"pre_target": "There was a large ",
			"post_target": " on her doorstep when she got home.",
			"boundary_index": 17,
			"boundary_shift": -328
		},
		{
			"morph_type": "complex",
			"list_index": 1,
			"indice": 50,
			"target": "sculptor",
			"preview": "snuletor",
			"sentence": "A very controversial X designed this piece last year.",
			"sentence_len": 60,
			"pre_target": "A very controversial ",
			"post_target": " designed this piece last year.",
			"boundary_index": 20,
			"boundary_shift": -280
		},
		{
			"morph_type": "complex",
			"list_index": 4,
			"indice": 41,
			"target": "zealous",
			"preview": "zelante",
			"sentence": "Some people are more X than others at church.",
			"sentence_len": 51,
			"pre_target": "Some people are more ",
			"post_target": " than others at church.",
			"boundary_index": 20,
			"boundary_shift": -280
		},
		{
			"morph_type": "complex",
			"list_index": 1,
			"indice": 58,
			"target": "humidity",
			"preview": "umiditi ",
			"sentence": "Try to maintain the right X and temperature to prevent spoiling.",
			"sentence_len": 71,
			"pre_target": "Try to maintain the right ",
			"post_target": " and temperature to prevent spoiling.",
			"boundary_index": 25,
			"boundary_shift": -200
		},
		{
			"morph_type": "complex",
			"list_index": 1,
			"indice": 48,
			"target": "gracious",
			"preview": "crapinus",
			"sentence": "While still sounding X and complimenting his employees he resigned.",
			"sentence_len": 74,
			"pre_target": "While still sounding ",
			"post_target": " and complimenting his employees he resigned.",
			"boundary_index": 20,
			"boundary_shift": -280
		},
		{
			"morph_type": "simple",
			"list_index": 2,
			"indice": 3,
			"target": "horror",
			"preview": "horror",
			"sentence": "We all have interesting\u00a0X stories we can tell, don't we?",
			"sentence_len": 61,
			"pre_target": "We all have interesting\u00a0",
			"post_target": " stories we can tell, don't we?",
			"boundary_index": 23,
			"boundary_shift": -232
		},
		{
			"morph_type": "complex",
			"list_index": 4,
			"indice": 42,
			"target": "bandages",
			"preview": "hkyqmfrp",
			"sentence": "Please change your X every two days for it to heal.",
			"sentence_len": 58,
			"pre_target": "Please change your ",
			"post_target": " every two days for it to heal.",
			"boundary_index": 18,
			"boundary_shift": -312
		},
		{
			"morph_type": "complex",
			"list_index": 4,
			"indice": 41,
			"target": "zealous",
			"preview": "mjkpvgw",
			"sentence": "Max was a little X at first when talking to strangers.",
			"sentence_len": 60,
			"pre_target": "Max was a little ",
			"post_target": " at first when talking to strangers.",
			"boundary_index": 16,
			"boundary_shift": -344
		},
		{
			"morph_type": "complex",
			"list_index": 3,
			"indice": 55,
			"target": "vigilance",
			"preview": "vagilasce",
			"sentence": "He needs to maintain X on the task at hand to avoid making mistakes.",
			"sentence_len": 76,
			"pre_target": "He needs to maintain ",
			"post_target": " on the task at hand to avoid making mistakes.",
			"boundary_index": 20,
			"boundary_shift": -280
		},
		{
			"morph_type": "complex",
			"list_index": 3,
			"indice": 35,
			"target": "audible",
			"preview": "aifible",
			"sentence": "The dog is definitely X when he spots a cat down the street.",
			"sentence_len": 66,
			"pre_target": "The dog is definitely ",
			"post_target": " when he spots a cat down the street.",
			"boundary_index": 21,
			"boundary_shift": -264
		},
		{
			"morph_type": "simple",
			"list_index": 3,
			"indice": 4,
			"target": "hybrid",
			"preview": "nobred",
			"sentence": "I invented X bicycles because the planet needed our help.",
			"sentence_len": 62,
			"pre_target": "I invented ",
			"post_target": " bicycles because the planet needed our help.",
			"boundary_index": 10,
			"boundary_shift": -440
		},
		{
			"morph_type": "complex",
			"list_index": 4,
			"indice": 44,
			"target": "firmness",
			"preview": "btjwqdyl",
			"sentence": "She detected an unusual X during a routine examination.",
			"sentence_len": 62,
			"pre_target": "She detected an unusual ",
			"post_target": " during a routine examination.",
			"boundary_index": 23,
			"boundary_shift": -232
		},
		{
			"morph_type": "simple",
			"list_index": 3,
			"indice": 12,
			"target": "nostril",
			"preview": "narice ",
			"sentence": "From the opposing X the water will run out and into the sink.",
			"sentence_len": 67,
			"pre_target": "From the opposing ",
			"post_target": " the water will run out and into the sink.",
			"boundary_index": 17,
			"boundary_shift": -328
		},
		{
			"morph_type": "simple",
			"list_index": 4,
			"indice": 18,
			"target": "recruit",
			"preview": "xzmdnbq",
			"sentence": "It looked like the newest X was going to fail his exams.",
			"sentence_len": 62,
			"pre_target": "It looked like the newest ",
			"post_target": " was going to fail his exams.",
			"boundary_index": 25,
			"boundary_shift": -200
		},
		{
			"morph_type": "simple",
			"list_index": 1,
			"indice": 20,
			"target": "rhythm",
			"preview": "romto ",
			"sentence": "He found a good X in the second quarter and scored thirty points.",
			"sentence_len": 70,
			"pre_target": "He found a good ",
			"post_target": " in the second quarter and scored thirty points.",
			"boundary_index": 15,
			"boundary_shift": -360
		},
		{
			"morph_type": "complex",
			"list_index": 2,
			"indice": 37,
			"target": "furious",
			"preview": "furious",
			"sentence": "Brian was clearly X about the grade he got for his final exam.",
			"sentence_len": 68,
			"pre_target": "Brian was clearly ",
			"post_target": " about the grade he got for his final exam.",
			"boundary_index": 17,
			"boundary_shift": -328
		},
		{
			"morph_type": "simple",
			"list_index": 2,
			"indice": 10,
			"target": "mountain",
			"preview": "qslzwyfr",
			"sentence": "After this one there will be another X for us to climb before the end.",
			"sentence_len": 77,
			"pre_target": "After this one there will be another ",
			"post_target": " for us to climb before the end.",
			"boundary_index": 36,
			"boundary_shift": -24
		},
		{
			"morph_type": "simple",
			"list_index": 2,
			"indice": 13,
			"target": "paddle",
			"preview": "jxnhvr",
			"sentence": "Only one old blue X was left in the boat when they checked.",
			"sentence_len": 64,
			"pre_target": "Only one old blue ",
			"post_target": " was left in the boat when they checked.",
			"boundary_index": 17,
			"boundary_shift": -328
		},
		{
			"morph_type": "complex",
			"list_index": 3,
			"indice": 62,
			"target": "asthmatic",
			"preview": "ostamati ",
			"sentence": "Children often experience X attacks as a result of tobacco smoke.",
			"sentence_len": 73,
			"pre_target": "Children often experience ",
			"post_target": " attacks as a result of tobacco smoke.",
			"boundary_index": 25,
			"boundary_shift": -200
		},
		{
			"morph_type": "complex",
			"list_index": 2,
			"indice": 40,
			"target": "soloist",
			"preview": "soloist",
			"sentence": "The only X in the orchestra was a violin player.",
			"sentence_len": 54,
			"pre_target": "The only ",
			"post_target": " in the orchestra was a violin player.",
			"boundary_index": 8,
			"boundary_shift": -472
		},
		{
			"morph_type": "simple",
			"list_index": 3,
			"indice": 16,
			"target": "platoon",
			"preview": "plutian",
			"sentence": "Last summer our entire X went through training runs every morning.",
			"sentence_len": 72,
			"pre_target": "Last summer our entire ",
			"post_target": " went through training runs every morning.",
			"boundary_index": 22,
			"boundary_shift": -248
		},
		{
			"morph_type": "complex",
			"list_index": 3,
			"indice": 56,
			"target": "european",
			"preview": "erropea ",
			"sentence": "That's a very X point of view on recycling.",
			"sentence_len": 50,
			"pre_target": "That's a very ",
			"post_target": " point of view on recycling.",
			"boundary_index": 13,
			"boundary_shift": -392
		},
		{
			"morph_type": "complex",
			"list_index": 2,
			"indice": 40,
			"target": "soloist",
			"preview": "rbgvhkf",
			"sentence": "Jessica was a former X for the national orchestra in Paris.",
			"sentence_len": 65,
			"pre_target": "Jessica was a former ",
			"post_target": " for the national orchestra in Paris.",
			"boundary_index": 20,
			"boundary_shift": -280
		},
		{
			"morph_type": "complex",
			"list_index": 3,
			"indice": 32,
			"target": "arcade",
			"preview": "aucode",
			"sentence": "Find the nearest local X and gamble your money away.",
			"sentence_len": 57,
			"pre_target": "Find the nearest local ",
			"post_target": " and gamble your money away.",
			"boundary_index": 22,
			"boundary_shift": -248
		},
		{
			"morph_type": "complex",
			"list_index": 3,
			"indice": 33,
			"target": "sanity",
			"preview": "sanit\u00e0",
			"sentence": "Let's bring some X back into this debate.",
			"sentence_len": 46,
			"pre_target": "Let's bring some ",
			"post_target": " back into this debate.",
			"boundary_index": 16,
			"boundary_shift": -344
		},
		{
			"morph_type": "simple",
			"list_index": 4,
			"indice": 24,
			"target": "sponge",
			"preview": "spugna",
			"sentence": "A large square X sat on the side of the kitchen sink.",
			"sentence_len": 58,
			"pre_target": "A large square ",
			"post_target": " sat on the side of the kitchen sink.",
			"boundary_index": 14,
			"boundary_shift": -376
		},
		{
			"morph_type": "simple",
			"list_index": 3,
			"indice": 9,
			"target": "molecule",
			"preview": "molecola",
			"sentence": "Even a single X remaining is incredibly unlikely.",
			"sentence_len": 56,
			"pre_target": "Even a single ",
			"post_target": " remaining is incredibly unlikely.",
			"boundary_index": 13,
			"boundary_shift": -392
		},
		{
			"morph_type": "simple",
			"list_index": 1,
			"indice": 31,
			"target": "yellow",
			"preview": "gollia",
			"sentence": "There were large X plates on the table for the main course.",
			"sentence_len": 64,
			"pre_target": "There were large ",
			"post_target": " plates on the table for the main course.",
			"boundary_index": 16,
			"boundary_shift": -344
		},
		{
			"morph_type": "complex",
			"list_index": 1,
			"indice": 49,
			"target": "pianists",
			"preview": "pianists",
			"sentence": "She wanted three X in the concert but only two arrived.",
			"sentence_len": 62,
			"pre_target": "She wanted three ",
			"post_target": " in the concert but only two arrived.",
			"boundary_index": 16,
			"boundary_shift": -344
		},
		{
			"morph_type": "complex",
			"list_index": 3,
			"indice": 36,
			"target": "density",
			"preview": "densit\u00e0",
			"sentence": "We're at the right X to not float away into space.",
			"sentence_len": 56,
			"pre_target": "We're at the right ",
			"post_target": " to not float away into space.",
			"boundary_index": 18,
			"boundary_shift": -312
		},
		{
			"morph_type": "complex",
			"list_index": 2,
			"indice": 52,
			"target": "dignified",
			"preview": "dignified",
			"sentence": "We need to develop X human rights laws for refugees.",
			"sentence_len": 60,
			"pre_target": "We need to develop ",
			"post_target": " human rights laws for refugees.",
			"boundary_index": 18,
			"boundary_shift": -312
		},
		{
			"morph_type": "complex",
			"list_index": 3,
			"indice": 38,
			"target": "nervous",
			"preview": "neprous",
			"sentence": "She was especially X before the test since she hadn't studied.",
			"sentence_len": 68,
			"pre_target": "She was especially ",
			"post_target": " before the test since she hadn't studied.",
			"boundary_index": 18,
			"boundary_shift": -312
		},
		{
			"morph_type": "simple",
			"list_index": 3,
			"indice": 25,
			"target": "surprise",
			"preview": "sorpresa",
			"sentence": "I hope your X isn't going to be spoiled.",
			"sentence_len": 47,
			"pre_target": "I hope your ",
			"post_target": " isn't going to be spoiled.",
			"boundary_index": 11,
			"boundary_shift": -424
		},
		{
			"morph_type": "complex",
			"list_index": 1,
			"indice": 48,
			"target": "gracious",
			"preview": "gracious",
			"sentence": "My mother was always X with her house guests.",
			"sentence_len": 52,
			"pre_target": "My mother was always ",
			"post_target": " with her house guests.",
			"boundary_index": 20,
			"boundary_shift": -280
		},
		{
			"morph_type": "complex",
			"list_index": 3,
			"indice": 35,
			"target": "audible",
			"preview": "udibile",
			"sentence": "It was almost X how excited she was at the news.",
			"sentence_len": 54,
			"pre_target": "It was almost ",
			"post_target": " how excited she was at the news.",
			"boundary_index": 13,
			"boundary_shift": -392
		},
		{
			"morph_type": "complex",
			"list_index": 4,
			"indice": 43,
			"target": "eruption",
			"preview": "eruzione",
			"sentence": "Witnessing a sudden X is both scary and exciting.",
			"sentence_len": 56,
			"pre_target": "Witnessing a sudden ",
			"post_target": " is both scary and exciting.",
			"boundary_index": 19,
			"boundary_shift": -296
		},
		{
			"morph_type": "complex",
			"list_index": 2,
			"indice": 53,
			"target": "greatness",
			"preview": "wxlmhfyvk",
			"sentence": "George is exceptional at seeing X in someone young and training them.",
			"sentence_len": 77,
			"pre_target": "George is exceptional at seeing ",
			"post_target": " in someone young and training them.",
			"boundary_index": 31,
			"boundary_shift": -104
		},
		{
			"morph_type": "complex",
			"list_index": 3,
			"indice": 36,
			"target": "density",
			"preview": "donsiti",
			"sentence": "We need the right X of reflective bits to decrease the solar radiation.",
			"sentence_len": 77,
			"pre_target": "We need the right ",
			"post_target": " of reflective bits to decrease the solar radiation.",
			"boundary_index": 17,
			"boundary_shift": -328
		},
		{
			"morph_type": "complex",
			"list_index": 1,
			"indice": 50,
			"target": "sculptor",
			"preview": "sculptor",
			"sentence": "Charles was the only X to have understood what I wanted.",
			"sentence_len": 63,
			"pre_target": "Charles was the only ",
			"post_target": " to have understood what I wanted.",
			"boundary_index": 20,
			"boundary_shift": -280
		},
		{
			"morph_type": "simple",
			"list_index": 2,
			"indice": 10,
			"target": "mountain",
			"preview": "mountain",
			"sentence": "Reducing some of this X of paper would be nice.",
			"sentence_len": 54,
			"pre_target": "Reducing some of this ",
			"post_target": " of paper would be nice.",
			"boundary_index": 21,
			"boundary_shift": -264
		},
		{
			"morph_type": "complex",
			"list_index": 1,
			"indice": 46,
			"target": "genetics",
			"preview": "genetics",
			"sentence": "Due to your particular X you have an increased risk of cancer.",
			"sentence_len": 69,
			"pre_target": "Due to your particular ",
			"post_target": " you have an increased risk of cancer.",
			"boundary_index": 22,
			"boundary_shift": -248
		},
		{
			"morph_type": "complex",
			"list_index": 4,
			"indice": 59,
			"target": "jealousy",
			"preview": "fmdwqrzt",
			"sentence": "A touch of friendly X mixed with pleasure is how we talk to them.",
			"sentence_len": 72,
			"pre_target": "A touch of friendly ",
			"post_target": " mixed with pleasure is how we talk to them.",
			"boundary_index": 19,
			"boundary_shift": -296
		},
		{
			"morph_type": "simple",
			"list_index": 1,
			"indice": 5,
			"target": "hygiene",
			"preview": "hygiene",
			"sentence": "They put inside X items for the earthquake victims.",
			"sentence_len": 57,
			"pre_target": "They put inside ",
			"post_target": " items for the earthquake victims.",
			"boundary_index": 15,
			"boundary_shift": -360
		},
		{
			"morph_type": "simple",
			"list_index": 2,
			"indice": 27,
			"target": "theorem",
			"preview": "theorem",
			"sentence": "This is an impossible X for us to prove in a traditional way.",
			"sentence_len": 67,
			"pre_target": "This is an impossible ",
			"post_target": " for us to prove in a traditional way.",
			"boundary_index": 21,
			"boundary_shift": -264
		},
		{
			"morph_type": "complex",
			"list_index": 4,
			"indice": 44,
			"target": "firmness",
			"preview": "fermezza",
			"sentence": "He showed the same X with his soldiers as with his children.",
			"sentence_len": 67,
			"pre_target": "He showed the same ",
			"post_target": " with his soldiers as with his children.",
			"boundary_index": 18,
			"boundary_shift": -312
		},
		{
			"morph_type": "simple",
			"list_index": 2,
			"indice": 26,
			"target": "synagogue",
			"preview": "synagogue",
			"sentence": "No doubt this X has the most beautiful exterior.",
			"sentence_len": 56,
			"pre_target": "No doubt this ",
			"post_target": " has the most beautiful exterior.",
			"boundary_index": 13,
			"boundary_shift": -392
		},
		{
			"morph_type": "complex",
			"list_index": 4,
			"indice": 39,
			"target": "signals",
			"preview": "segnali",
			"sentence": "He continued to display X on the side of the field to motivate players.",
			"sentence_len": 77,
			"pre_target": "He continued to display ",
			"post_target": " on the side of the field to motivate players.",
			"boundary_index": 23,
			"boundary_shift": -232
		},
		{
			"morph_type": "simple",
			"list_index": 2,
			"indice": 0,
			"target": "change",
			"preview": "qdzljy",
			"sentence": "There has been no\u00a0huge X in its use in the last decade.",
			"sentence_len": 60,
			"pre_target": "There has been no\u00a0huge ",
			"post_target": " in its use in the last decade.",
			"boundary_index": 22,
			"boundary_shift": -248
		},
		{
			"morph_type": "simple",
			"list_index": 2,
			"indice": 26,
			"target": "synagogue",
			"preview": "lzcrjhwfx",
			"sentence": "You may expect every X to be different in some way.",
			"sentence_len": 59,
			"pre_target": "You may expect every ",
			"post_target": " to be different in some way.",
			"boundary_index": 20,
			"boundary_shift": -280
		},
		{
			"morph_type": "simple",
			"list_index": 4,
			"indice": 7,
			"target": "lettuce",
			"preview": "lattuga",
			"sentence": "To their frustration only some X and corn\u00a0would grow in its poor soil.",
			"sentence_len": 76,
			"pre_target": "To their frustration only some ",
			"post_target": " and corn\u00a0would grow in its poor soil.",
			"boundary_index": 30,
			"boundary_shift": -120
		},
		{
			"morph_type": "complex",
			"list_index": 4,
			"indice": 43,
			"target": "eruption",
			"preview": "yhsdcqjk",
			"sentence": "A completely unexpected X from the moka sprayed coffee over the walls.",
			"sentence_len": 77,
			"pre_target": "A completely unexpected ",
			"post_target": " from the moka sprayed coffee over the walls.",
			"boundary_index": 23,
			"boundary_shift": -232
		},
		{
			"morph_type": "complex",
			"list_index": 2,
			"indice": 54,
			"target": "sensitive",
			"preview": "qhgrxzpcw",
			"sentence": "There is possibly X data that has been transmitted to scammers.",
			"sentence_len": 71,
			"pre_target": "There is possibly ",
			"post_target": " data that has been transmitted to scammers.",
			"boundary_index": 17,
			"boundary_shift": -328
		},
		{
			"morph_type": "complex",
			"list_index": 2,
			"indice": 60,
			"target": "northern",
			"preview": "qsxpzmbk",
			"sentence": "This is the great X tradition of coffee breaks called fika.",
			"sentence_len": 66,
			"pre_target": "This is the great ",
			"post_target": " tradition of coffee breaks called fika.",
			"boundary_index": 17,
			"boundary_shift": -328
		},
		{
			"morph_type": "simple",
			"list_index": 3,
			"indice": 16,
			"target": "platoon",
			"preview": "plotone",
			"sentence": "Those in the first X were the ones who get hurt the worst.",
			"sentence_len": 64,
			"pre_target": "Those in the first ",
			"post_target": " were the ones who get hurt the worst.",
			"boundary_index": 18,
			"boundary_shift": -312
		},
		{
			"morph_type": "complex",
			"list_index": 2,
			"indice": 53,
			"target": "greatness",
			"preview": "greatness",
			"sentence": "Make your way towards X by pushing yourself to be better.",
			"sentence_len": 65,
			"pre_target": "Make your way towards ",
			"post_target": " by pushing yourself to be better.",
			"boundary_index": 21,
			"boundary_shift": -264
		},
		{
			"morph_type": "complex",
			"list_index": 3,
			"indice": 55,
			"target": "vigilance",
			"preview": "vigilanza",
			"sentence": "I appreciate your ongoing X in getting the truth out there.",
			"sentence_len": 67,
			"pre_target": "I appreciate your ongoing ",
			"post_target": " in getting the truth out there.",
			"boundary_index": 25,
			"boundary_shift": -200
		},
		{
			"morph_type": "simple",
			"list_index": 1,
			"indice": 23,
			"target": "spinach",
			"preview": "spinach",
			"sentence": "The look of the brownish X didn't appeal to him at all.",
			"sentence_len": 61,
			"pre_target": "The look of the brownish ",
			"post_target": " didn't appeal to him at all.",
			"boundary_index": 24,
			"boundary_shift": -216
		},
		{
			"morph_type": "simple",
			"list_index": 2,
			"indice": 1,
			"target": "example",
			"preview": "ynbhrzv",
			"sentence": "We must consider the previous X of collaboration between the two labs.",
			"sentence_len": 76,
			"pre_target": "We must consider the previous ",
			"post_target": " of collaboration between the two labs.",
			"boundary_index": 29,
			"boundary_shift": -136
		},
		{
			"morph_type": "simple",
			"list_index": 2,
			"indice": 11,
			"target": "nephew",
			"preview": "xkrvmy",
			"sentence": "Only a special X would agree to help his uncle for a year.",
			"sentence_len": 63,
			"pre_target": "Only a special ",
			"post_target": " would agree to help his uncle for a year.",
			"boundary_index": 14,
			"boundary_shift": -376
		},
		{
			"morph_type": "simple",
			"list_index": 3,
			"indice": 19,
			"target": "resource",
			"preview": "risorsa ",
			"sentence": "It's an amazing X for young students interested in biology.",
			"sentence_len": 66,
			"pre_target": "It's an amazing ",
			"post_target": " for young students interested in biology.",
			"boundary_index": 15,
			"boundary_shift": -360
		},
		{
			"morph_type": "simple",
			"list_index": 2,
			"indice": 15,
			"target": "plaque",
			"preview": "plaque",
			"sentence": "Choosing the right X to buy is not quite easy.",
			"sentence_len": 51,
			"pre_target": "Choosing the right ",
			"post_target": " to buy is not quite easy.",
			"boundary_index": 18,
			"boundary_shift": -312
		},
		{
			"morph_type": "complex",
			"list_index": 2,
			"indice": 45,
			"target": "fortress",
			"preview": "ydnxklgm",
			"sentence": "John had made a\u00a0personal\u00a0X of his library and lived as a scholar.",
			"sentence_len": 72,
			"pre_target": "John had made a\u00a0personal\u00a0",
			"post_target": " of his library and lived as a scholar.",
			"boundary_index": 24,
			"boundary_shift": -216
		},
		{
			"morph_type": "simple",
			"list_index": 3,
			"indice": 25,
			"target": "surprise",
			"preview": "sartrine",
			"sentence": "John could always X Jane on their anniversary.",
			"sentence_len": 53,
			"pre_target": "John could always ",
			"post_target": " Jane on their anniversary.",
			"boundary_index": 17,
			"boundary_shift": -328
		},
		{
			"morph_type": "simple",
			"list_index": 2,
			"indice": 0,
			"target": "change",
			"preview": "change",
			"sentence": "Looks like more\u00a0X than anyone expected at the beginning of the project.",
			"sentence_len": 76,
			"pre_target": "Looks like more\u00a0",
			"post_target": " than anyone expected at the beginning of the project.",
			"boundary_index": 15,
			"boundary_shift": -360
		},
		{
			"morph_type": "simple",
			"list_index": 2,
			"indice": 3,
			"target": "horror",
			"preview": "mgdkzq",
			"sentence": "Think of it as a typical\u00a0X film where the monsters end up defeated.",
			"sentence_len": 72,
			"pre_target": "Think of it as a typical\u00a0",
			"post_target": " film where the monsters end up defeated.",
			"boundary_index": 24,
			"boundary_shift": -216
		},
		{
			"morph_type": "complex",
			"list_index": 3,
			"indice": 33,
			"target": "sanity",
			"preview": "manitu",
			"sentence": "Any hope of a future X depended on our willingness to listen.",
			"sentence_len": 66,
			"pre_target": "Any hope of a future ",
			"post_target": " depended on our willingness to listen.",
			"boundary_index": 20,
			"boundary_shift": -280
		},
		{
			"morph_type": "simple",
			"list_index": 2,
			"indice": 14,
			"target": "parcel",
			"preview": "hfjmwt",
			"sentence": "Jane recognised the bright X containing the books she had ordered.",
			"sentence_len": 71,
			"pre_target": "Jane recognised the bright ",
			"post_target": " containing the books she had ordered.",
			"boundary_index": 26,
			"boundary_shift": -184
		},
		{
			"morph_type": "simple",
			"list_index": 1,
			"indice": 31,
			"target": "yellow",
			"preview": "yellow",
			"sentence": "Yesterday he declared\u00a0X\u00a0alerts for several areas.",
			"sentence_len": 54,
			"pre_target": "Yesterday he declared\u00a0",
			"post_target": "\u00a0alerts for several areas.",
			"boundary_index": 21,
			"boundary_shift": -264
		},
		{
			"morph_type": "complex",
			"list_index": 4,
			"indice": 42,
			"target": "bandages",
			"preview": "bendaggi",
			"sentence": "There were clean X left on the floor of the hospital.",
			"sentence_len": 60,
			"pre_target": "There were clean ",
			"post_target": " left on the floor of the hospital.",
			"boundary_index": 16,
			"boundary_shift": -344
		},
		{
			"morph_type": "simple",
			"list_index": 1,
			"indice": 20,
			"target": "rhythm",
			"preview": "rhythm",
			"sentence": "It has a real X that you can easily dance to.",
			"sentence_len": 50,
			"pre_target": "It has a real ",
			"post_target": " that you can easily dance to.",
			"boundary_index": 13,
			"boundary_shift": -392
		},
		{
			"morph_type": "simple",
			"list_index": 3,
			"indice": 4,
			"target": "hybrid",
			"preview": "ibrido ",
			"sentence": "The most recent X cars are even more fuel-efficient.",
			"sentence_len": 58,
			"pre_target": "The most recent ",
			"post_target": " cars are even more fuel-efficient.",
			"boundary_index": 15,
			"boundary_shift": -360
		},
		{
			"morph_type": "complex",
			"list_index": 3,
			"indice": 47,
			"target": "glorious",
			"preview": "gloriosa",
			"sentence": "We really have X weather today with this sun.",
			"sentence_len": 52,
			"pre_target": "We really have ",
			"post_target": " weather today with this sun.",
			"boundary_index": 14,
			"boundary_shift": -376
		},
		{
			"morph_type": "complex",
			"list_index": 2,
			"indice": 54,
			"target": "sensitive",
			"preview": "sensitive",
			"sentence": "The Arctic Ocean is more X to changes in climate.",
			"sentence_len": 57,
			"pre_target": "The Arctic Ocean is more ",
			"post_target": " to changes in climate.",
			"boundary_index": 24,
			"boundary_shift": -216
		},
		{
			"morph_type": "complex",
			"list_index": 1,
			"indice": 51,
			"target": "violence",
			"preview": "vielerce",
			"sentence": "Let's talk about X in a home environment between parents.",
			"sentence_len": 64,
			"pre_target": "Let's talk about ",
			"post_target": " in a home environment between parents.",
			"boundary_index": 16,
			"boundary_shift": -344
		},
		{
			"morph_type": "simple",
			"list_index": 4,
			"indice": 2,
			"target": "genius",
			"preview": "genio ",
			"sentence": "He has a certain X matched by his sympathy for all kinds of behaviour.",
			"sentence_len": 75,
			"pre_target": "He has a certain ",
			"post_target": " matched by his sympathy for all kinds of behaviour.",
			"boundary_index": 16,
			"boundary_shift": -344
		},
		{
			"morph_type": "complex",
			"list_index": 4,
			"indice": 57,
			"target": "historic",
			"preview": "jznbvpdw",
			"sentence": "For this potentially X event to occur we need genuine cooperation.",
			"sentence_len": 73,
			"pre_target": "For this potentially ",
			"post_target": " event to occur we need genuine cooperation.",
			"boundary_index": 20,
			"boundary_shift": -280
		},
		{
			"morph_type": "complex",
			"list_index": 2,
			"indice": 60,
			"target": "northern",
			"preview": "northern",
			"sentence": "It's located between X Spain and the south of France.",
			"sentence_len": 60,
			"pre_target": "It's located between ",
			"post_target": " Spain and the south of France.",
			"boundary_index": 20,
			"boundary_shift": -280
		},
		{
			"morph_type": "simple",
			"list_index": 2,
			"indice": 1,
			"target": "example",
			"preview": "example",
			"sentence": "It has shown them a true\u00a0X of how to fight back against wars.\u00a0",
			"sentence_len": 68,
			"pre_target": "It has shown them a true\u00a0",
			"post_target": " of how to fight back against wars.\u00a0",
			"boundary_index": 24,
			"boundary_shift": -216
		},
		{
			"morph_type": "simple",
			"list_index": 4,
			"indice": 30,
			"target": "vehicle",
			"preview": "veicolo",
			"sentence": "It's definitely a great X for a large family.",
			"sentence_len": 51,
			"pre_target": "It's definitely a great ",
			"post_target": " for a large family.",
			"boundary_index": 23,
			"boundary_shift": -232
		},
		{
			"morph_type": "complex",
			"list_index": 3,
			"indice": 32,
			"target": "arcade",
			"preview": "arcata",
			"sentence": "An unfamiliar narrow X opened upon an inner flowery court.",
			"sentence_len": 63,
			"pre_target": "An unfamiliar narrow ",
			"post_target": " opened upon an inner flowery court.",
			"boundary_index": 20,
			"boundary_shift": -280
		},
		{
			"morph_type": "simple",
			"list_index": 2,
			"indice": 21,
			"target": "school",
			"preview": "zyntdg",
			"sentence": "With so much X work to do they didn't have time to travel much.",
			"sentence_len": 68,
			"pre_target": "With so much ",
			"post_target": " work to do they didn't have time to travel much.",
			"boundary_index": 12,
			"boundary_shift": -408
		},
		{
			"morph_type": "simple",
			"list_index": 3,
			"indice": 28,
			"target": "throne",
			"preview": "torne ",
			"sentence": "Matthew dashed into the crowded X room with the pineapple.",
			"sentence_len": 63,
			"pre_target": "Matthew dashed into the crowded ",
			"post_target": " room with the pineapple.",
			"boundary_index": 31,
			"boundary_shift": -104
		},
		{
			"morph_type": "simple",
			"list_index": 3,
			"indice": 17,
			"target": "prophet",
			"preview": "profeta",
			"sentence": "In centuries no other X had managed to unite them as he did.",
			"sentence_len": 66,
			"pre_target": "In centuries no other ",
			"post_target": " had managed to unite them as he did.",
			"boundary_index": 21,
			"boundary_shift": -264
		},
		{
			"morph_type": "simple",
			"list_index": 2,
			"indice": 13,
			"target": "paddle",
			"preview": "paddle",
			"sentence": "We looked for the missing X all day but couldn't find it.",
			"sentence_len": 62,
			"pre_target": "We looked for the missing ",
			"post_target": " all day but couldn't find it.",
			"boundary_index": 25,
			"boundary_shift": -200
		},
		{
			"morph_type": "simple",
			"list_index": 2,
			"indice": 21,
			"target": "school",
			"preview": "school",
			"sentence": "Linda always disliked X when it was sunny outside.",
			"sentence_len": 55,
			"pre_target": "Linda always disliked ",
			"post_target": " when it was sunny outside.",
			"boundary_index": 21,
			"boundary_shift": -264
		},
		{
			"morph_type": "simple",
			"list_index": 4,
			"indice": 30,
			"target": "vehicle",
			"preview": "pyjmgqd",
			"sentence": "Yesterday I saw another X on that street in the middle of the day.",
			"sentence_len": 72,
			"pre_target": "Yesterday I saw another ",
			"post_target": " on that street in the middle of the day.",
			"boundary_index": 23,
			"boundary_shift": -232
		},
		{
			"morph_type": "simple",
			"list_index": 3,
			"indice": 12,
			"target": "nostril",
			"preview": "nitiro ",
			"sentence": "In the right X there was a little circular piercing.",
			"sentence_len": 58,
			"pre_target": "In the right ",
			"post_target": " there was a little circular piercing.",
			"boundary_index": 12,
			"boundary_shift": -408
		}
	]
]